tests/__init__.py
tests/conftest.py
tests/fixtures.py
tests/settings.py
tests/test_pages.py
tests/urls.py
tests/testapp/__init__.py
tests/testapp/factories.py
tests/testapp/models.py
tests/testapp/migrations/0001_initial.py
tests/testapp/migrations/__init__.py
tests/testapp/templates/testapp/automatic_redirects_test_index_page.html
tests/testapp/templates/testapp/automatic_redirects_test_page.html
wagtail_automatic_redirects/__init__.py
wagtail_automatic_redirects/apps.py
wagtail_automatic_redirects/signal_handlers.py
wagtail_automatic_redirects-1.1.5.dist-info/LICENSE
wagtail_automatic_redirects-1.1.5.dist-info/METADATA
wagtail_automatic_redirects-1.1.5.dist-info/WHEEL
wagtail_automatic_redirects-1.1.5.dist-info/top_level.txt
wagtail_automatic_redirects-1.1.5.dist-info/RECORD
