Metadata-Version: 2.1
Name: wagtail-automatic-redirects
Version: 1.1.5
Summary: Helpers for Wagtail Redirects
Home-page: https://github.com/themotleyfool/wagtail-automatic-redirects
Author: Parbhat Puri
Author-email: me@parbhatpuri.com
License: UNKNOWN
Platform: UNKNOWN
Classifier: Intended Audience :: Developers
Classifier: Operating System :: OS Independent
Classifier: Topic :: Software Development
Classifier: Programming Language :: Python
Classifier: Programming Language :: Python :: 3
Classifier: Framework :: Django
Classifier: Framework :: Wagtail
Requires-Python: >=3.6
Requires-Dist: wagtail
Provides-Extra: test
Requires-Dist: pytest-django ; extra == 'test'
Requires-Dist: wagtail-factories ; extra == 'test'
Requires-Dist: pytest ; extra == 'test'
